respyrar/__init__.py
respyrar/main.py
respyrar-0.0.7.dist-info/LICENSE
respyrar-0.0.7.dist-info/METADATA
respyrar-0.0.7.dist-info/WHEEL
respyrar-0.0.7.dist-info/top_level.txt
respyrar-0.0.7.dist-info/RECORD
