Metadata-Version: 2.1
Name: respyrar
Version: 0.0.7
Summary: Monitor air quality - Monitoreá la calidad del aire
Author-email: Martín Amigo <martinamigo97@gmail.com>
License: Copyright 2022 ObSA - Observatorio de Salud y Ambiente, CeNDIE 
Keywords: air,emissions,no2,earth,engine,geoscience,atmospheric
Classifier: License :: OSI Approved :: MIT License
Classifier: Programming Language :: Python
Classifier: Programming Language :: Python :: 3
Requires-Python: >=3.10
License-File: LICENSE
Requires-Dist: earthengine-api
Requires-Dist: numpy
Requires-Dist: pandas
Requires-Dist: isoweek
Requires-Dist: matplotlib
Requires-Dist: Cython
Requires-Dist: cartopy
Requires-Dist: scipy
Requires-Dist: statsmodels
Requires-Dist: wheel
Requires-Dist: tomli ; python_version < "3.11"
